gecosistema_core/__init__.py
gecosistema_core/compression.py
gecosistema_core/datatypes.py
gecosistema_core/excel.py
gecosistema_core/exceptions.py
gecosistema_core/execution.py
gecosistema_core/filesystem.py
gecosistema_core/http.py
gecosistema_core/maths.py
gecosistema_core/platform.py
gecosistema_core/stime.py
gecosistema_core/strings.py
gecosistema_core/xml_utils.py
gecosistema_core-0.0.200.dist-info/LICENSE
gecosistema_core-0.0.200.dist-info/METADATA
gecosistema_core-0.0.200.dist-info/WHEEL
gecosistema_core-0.0.200.dist-info/top_level.txt
gecosistema_core-0.0.200.dist-info/RECORD
