Metadata-Version: 2.1
Name: gecosistema-core
Version: 0.0.200
Summary: A small example package
Home-page: https://github.com/valluzzi/gecosistema_core.git
Author: Valerio Luzzi
Author-email: valluzzi@gmail.com
License: UNKNOWN
Platform: UNKNOWN
Classifier: Programming Language :: Python :: 2
Classifier: License :: OSI Approved :: MIT License
Classifier: Operating System :: OS Independent
Requires-Dist: jinja2
Requires-Dist: six
Requires-Dist: argparse
Requires-Dist: xmljson
Requires-Dist: openpyxl
Requires-Dist: xlrd
Requires-Dist: xlwt
Requires-Dist: xlutils
Requires-Dist: numpy
Requires-Dist: rarfile
